__init__.py
weather/__init__.py
weather/weather.py
oweatherm-0.5.2.dist-info/METADATA
oweatherm-0.5.2.dist-info/WHEEL
oweatherm-0.5.2.dist-info/top_level.txt
oweatherm-0.5.2.dist-info/RECORD
