Metadata-Version: 2.1
Name: oweatherm
Version: 0.5.2
Summary: Weather from OpenWeatherMap
Home-page: UNKNOWN
Author: nedogimov
Author-email: mrfoxit01@gmail.com
License: Apache License, Version 2.0
Platform: UNKNOWN
Classifier: License :: OSI Approved :: Apache Software License
Classifier: Operating System :: OS Independent
Classifier: Programming Language :: Python
Classifier: Programming Language :: Python :: 3
Classifier: Programming Language :: Python :: 3.4
Classifier: Programming Language :: Python :: 3.5
Classifier: Programming Language :: Python :: 3.6
Classifier: Programming Language :: Python :: 3.7
Classifier: Programming Language :: Python :: Implementation :: PyPy
Classifier: Programming Language :: Python :: Implementation :: CPython
Requires-Dist: requests
